setup.py
distributions9/Binomialdistribution.py
distributions9/Gaussiandistribution.py
distributions9/Generaldistribution.py
distributions9/__init__.py
distributions9.egg-info/PKG-INFO
distributions9.egg-info/SOURCES.txt
distributions9.egg-info/dependency_links.txt
distributions9.egg-info/not-zip-safe
distributions9.egg-info/top_level.txt