Metadata-Version: 1.0
Name: distributions9
Version: 0.1
Summary: Gaussian and Binomial distributions
Home-page: UNKNOWN
Author: Parth Shah
Author-email: parthrrs19@gmail.com
License: UNKNOWN
Platform: UNKNOWN
